LICENSE
MANIFEST.in
README.rst
setup.py
dsrtp/__init__.py
dsrtp.egg-info/PKG-INFO
dsrtp.egg-info/SOURCES.txt
dsrtp.egg-info/dependency_links.txt
dsrtp.egg-info/requires.txt
dsrtp.egg-info/top_level.txt
dsrtp/ext/ext.c
script/dsrtp
test/test_dsrtp.py