Metadata-Version: 1.1
Name: dsrtp
Version: 0.2.0
Summary: Frontend for decrypting captured SRTP packets.
Home-page: https://github.com/mayfieldrobotics/dsrtp/
Author: Mayfield Robotics
Author-email: dev+dsrtp@mayfieldrobotics.com
License: MIT
Platform: any
Classifier: Intended Audience :: Developers
Classifier: License :: OSI Approved :: BSD License
Classifier: Operating System :: OS Independent
Classifier: Programming Language :: Python
Classifier: Topic :: Software Development :: Libraries :: Python Modules
